ReadEm/__init__.py
ReadEm/serve.py
ReadEm/assets/__init__.py
ReadEm/assets/app.css
ReadEm/assets/app.js
ReadEm/assets/github.css
ReadEm/templates/__init__.py
ReadEm/templates/default.html
ReadEm-1.0.2.dist-info/LICENSE.txt
ReadEm-1.0.2.dist-info/METADATA
ReadEm-1.0.2.dist-info/WHEEL
ReadEm-1.0.2.dist-info/top_level.txt
ReadEm-1.0.2.dist-info/RECORD
